advisor.py
agrivisor-1.0.dist-info/METADATA
agrivisor-1.0.dist-info/WHEEL
agrivisor-1.0.dist-info/top_level.txt
agrivisor-1.0.dist-info/RECORD
