Metadata-Version: 2.4
Name: agrivisor
Version: 1.0
Summary: Agriculture advisory engine for weather-based recommendations
Author-email: Muzammil Sarwar <x24212857@student.ncirl.ie>
Requires-Python: >=3.10
Requires-Dist: pydantic
